{
  "recordId": "rec07YAC9KOwr6iZv",
  "source": "Airtable Listings_V1 (base appp8inLAGTg4qpEZ / table tbldMjKBgPiq45Jjs)",
  "fetch": "read-only via Airtable MCP on 2026-06-16; mapped to the Listing shape per lib/airtable.ts LISTING_NAME_MAP. Blank Airtable cells -> null.",
  "note": "Detroit MI, Outreach_Status=Texted, Live_Status=Active, MLS_Status=ACTIVE, Last_Verified 2026-06-14 (fresh vs a mid-June run). Clears the full Pre-Outreach gate and reaches Pre-Send. Real_ARV_Median 99672 is ABOVE List_Price 79000 (sane) -> the buy-box ARV path penciled, but the ceiling lands below the low-opener floor -> routed to flat 65%.",
  "storedOpener": { "roughOpenerAmount": null, "openerBasis": null },
  "listing": {
    "id": "rec07YAC9KOwr6iZv",
    "createdTime": "2026-05-01T19:21:29.000Z",
    "address": "15875 Strathmoor St",
    "city": "Detroit",
    "zip": "48227",
    "state": "MI",
    "listPrice": 79000,
    "mao": 51250,
    "dom": null,
    "offerTier": null,
    "liveStatus": "Active",
    "executionPath": null,
    "outreachStatus": "Texted",
    "lastOutreachDate": "2026-06-07",
    "agentName": "Charles Campbell",
    "agentPhone": "561-632-9673",
    "agentEmail": "CCampbell@ListWithFreedom.com",
    "verificationUrl": "https://www.redfin.com/MI/Detroit/15875-Strathmoor-St-48227/home/98522860",
    "notes": "Redfin property page returned schema.org InStock and no restriction keywords were detected.",
    "distressScore": null,
    "distressBucket": null,
    "bedrooms": 3,
    "bathrooms": null,
    "buildingSqFt": 1468,
    "yearBuilt": null,
    "portfolioDetected": false,
    "stageCalc": null,
    "approvedForOutreach": false,
    "flipScore": null,
    "offMarketOverride": false,
    "restrictionText": null,
    "ddChecklist": null,
    "doNotText": false,
    "state": "MI",
    "sourceVersion": "v1_legacy",
    "actionHoldUntil": null,
    "actionCardState": null,
    "lastInboundAt": null,
    "lastOutboundAt": null,
    "lastEmailOutreachDate": null,
    "envelopeId": null,
    "mlsStatus": "ACTIVE",
    "propertyType": "Single Family",
    "priceDropCount": null,
    "lastVerified": "2026-06-14T01:30:27.823Z",
    "pipelineStage": null,
    "realArvMedian": 99672,
    "arvConfidence": "MED",
    "estRehab": 37434,
    "estRehabMid": 37434,
    "estimatedMonthlyRent": 1360,
    "arvCompCount": 3,
    "arvCompAvgPrSqFt": 68,
    "wholesaleFeeTarget": null,
    "roughOpenerAmount": null,
    "openerBasis": null
  }
}
